ensite/__init__.py
ensite/ensite.py
apache_ensite-0.2.2.dist-info/LICENSE
apache_ensite-0.2.2.dist-info/METADATA
apache_ensite-0.2.2.dist-info/WHEEL
apache_ensite-0.2.2.dist-info/entry_points.txt
apache_ensite-0.2.2.dist-info/top_level.txt
apache_ensite-0.2.2.dist-info/RECORD
