Metadata-Version: 2.1
Name: apache-ensite
Version: 0.2.2
Summary: Apache 2 Configuration file management utilities
Home-page: https://github.com/zathras777/apache-ensite
Author: david reid
Author-email: zathrasorama@gmail.com
License: Unlicense
Download-URL: https://github.com/zathras777/apache-ensite/archive/0.2.1.zip
Keywords: apache unix configuration
Platform: UNKNOWN
Classifier: Development Status :: 3 - Alpha
Classifier: Operating System :: Unix
Classifier: Intended Audience :: System Administrators
Classifier: Programming Language :: Python :: 2.7
Classifier: Programming Language :: Python :: 3.4
Classifier: Topic :: Internet :: WWW/HTTP :: HTTP Servers
